capsulecorp/__init__.py
capsulecorp/assets.py
capsulecorp/dataset.py
capsulecorp/query_driver.py
capsulecorp/version.py
capsulecorp/utilities/__init__.py
capsulecorp/utilities/databricks_utils.py
capsulecorp/utilities/datadog_utils.py
capsulecorp/utilities/general_utils.py
capsulecorp/utilities/github_utils.py
capsulecorp/utilities/mysql_utils.py
capsulecorp/utilities/pandas_utils.py
capsulecorp/utilities/postgresql_utils.py
capsulecorp/utilities/redact_utils.py
capsulecorp/utilities/s3_utils.py
capsulecorp/utilities/slack_utils.py
capsulecorp/utilities/spark_utils.py
tests/utilities/__init__.py
tests/utilities/test_general_utils.py
tests/utilities/test_mysql_utils.py
tests/utilities/test_pandas_utils.py
tests/utilities/test_redact_utils.py
tests/utilities/test_s3_utils.py
capsulecorp-0.2.20.dist-info/LICENSE
capsulecorp-0.2.20.dist-info/METADATA
capsulecorp-0.2.20.dist-info/WHEEL
capsulecorp-0.2.20.dist-info/top_level.txt
capsulecorp-0.2.20.dist-info/RECORD
