Metadata-Version: 2.1
Name: capsulecorp
Version: 0.2.20
Summary: General python utilities package for working with public cloud services and big data
Home-page: https://github.com/leealessandrini/capsulecorp
Author: Daniel Lee Alessandrini
Author-email: alessandrinil@gmail.com
Classifier: Development Status :: 3 - Alpha
Classifier: Programming Language :: Python :: 3.9
Requires-Python: >=3.9
License-File: LICENSE
Requires-Dist: pytest
Requires-Dist: pytest-cov
Requires-Dist: PyYAML
Requires-Dist: numpy
Requires-Dist: pandas
Requires-Dist: pyarrow
Requires-Dist: moto
Requires-Dist: boto3
Requires-Dist: psycopg2-binary ==2.9.3
Requires-Dist: PyMySQL
Requires-Dist: slack-sdk
Requires-Dist: tabulate
Requires-Dist: databricks-cli
Requires-Dist: PyGithub
Requires-Dist: scipy
Requires-Dist: marshmallow
Requires-Dist: datadog-api-client
